{
  "manifestVersion": "3.2",
  "proxies": [
    {
      "address": "0xeecA5682C8945B0e59150a418961eE71B100bf0C",
      "txHash": "0x8da7fe09b618e88f30a3d0799cfc4939e65895bc034d79f90f537abffa231650",
      "kind": "uups"
    },
    {
      "address": "0xFfDFDa7bbc6BE7B1383fBc4C77B38241cC0fBa8f",
      "txHash": "0x716516f91ca2bcd70335dea96b3ccf133f312bf1670c2df99f1017d397ee6296",
      "kind": "uups"
    },
    {
      "address": "0x9e176ee9B149D7acb0b8dF3511Df76E1b7972cC0",
      "txHash": "0xd8a39069f2bb1934cff07f5f2c24109cc0ae9cd6570f2355ed43c64e297e3e8e",
      "kind": "uups"
    },
    {
      "address": "0xfd1fAB2E969aE7eC95De81caf1240107a76963Dc",
      "txHash": "0xcf8e7e461488adfcc20b4813c90c244ef69d5a362c0ee5bb82e27d549e616705",
      "kind": "uups"
    }
  ],
  "impls": {
    "3f16e0524b2416dd9ac25b907b9c3ab736a4fb4746904988cdc7cc61828ba226": {
      "address": "0x24FdDc64587398A661f885c965BaBF7079E30c21",
      "txHash": "0xaeacdbe35b1a8868e77a09772cf68ccc709a6b5aa991ca50dc38d4437f6f9b4a",
      "layout": {
        "solcVersion": "0.8.28",
        "storage": [
          {
            "label": "_tokenIdCounter",
            "offset": 0,
            "slot": "0",
            "type": "t_uint256",
            "contract": "MarketplaceV1",
            "src": "contracts\\MarketplaceV1.sol:13"
          },
          {
            "label": "paymentToken",
            "offset": 0,
            "slot": "1",
            "type": "t_contract(IERC20)3152",
            "contract": "MarketplaceV1",
            "src": "contracts\\MarketplaceV1.sol:16"
          },
          {
            "label": "_tokenURIs",
            "offset": 0,
            "slot": "2",
            "type": "t_mapping(t_uint256,t_string_storage)",
            "contract": "MarketplaceV1",
            "src": "contracts\\MarketplaceV1.sol:19"
          },
          {
            "label": "listings",
            "offset": 0,
            "slot": "3",
            "type": "t_mapping(t_uint256,t_struct(Listing)8945_storage)",
            "contract": "MarketplaceV1",
            "src": "contracts\\MarketplaceV1.sol:29"
          }
        ],
        "types": {
          "t_address": {
            "label": "address",
            "numberOfBytes": "20"
          },
          "t_bool": {
            "label": "bool",
            "numberOfBytes": "1"
          },
          "t_mapping(t_address,t_bool)": {
            "label": "mapping(address => bool)",
            "numberOfBytes": "32"
          },
          "t_mapping(t_address,t_mapping(t_address,t_bool))": {
            "label": "mapping(address => mapping(address => bool))",
            "numberOfBytes": "32"
          },
          "t_mapping(t_address,t_uint256)": {
            "label": "mapping(address => uint256)",
            "numberOfBytes": "32"
          },
          "t_mapping(t_uint256,t_address)": {
            "label": "mapping(uint256 => address)",
            "numberOfBytes": "32"
          },
          "t_string_storage": {
            "label": "string",
            "numberOfBytes": "32"
          },
          "t_struct(ERC721Storage)240_storage": {
            "label": "struct ERC721Upgradeable.ERC721Storage",
            "members": [
              {
                "label": "_name",
                "type": "t_string_storage",
                "offset": 0,
                "slot": "0"
              },
              {
                "label": "_symbol",
                "type": "t_string_storage",
                "offset": 0,
                "slot": "1"
              },
              {
                "label": "_owners",
                "type": "t_mapping(t_uint256,t_address)",
                "offset": 0,
                "slot": "2"
              },
              {
                "label": "_balances",
                "type": "t_mapping(t_address,t_uint256)",
                "offset": 0,
                "slot": "3"
              },
              {
                "label": "_tokenApprovals",
                "type": "t_mapping(t_uint256,t_address)",
                "offset": 0,
                "slot": "4"
              },
              {
                "label": "_operatorApprovals",
                "type": "t_mapping(t_address,t_mapping(t_address,t_bool))",
                "offset": 0,
                "slot": "5"
              }
            ],
            "numberOfBytes": "192"
          },
          "t_struct(InitializableStorage)73_storage": {
            "label": "struct Initializable.InitializableStorage",
            "members": [
              {
                "label": "_initialized",
                "type": "t_uint64",
                "offset": 0,
                "slot": "0"
              },
              {
                "label": "_initializing",
                "type": "t_bool",
                "offset": 8,
                "slot": "0"
              }
            ],
            "numberOfBytes": "32"
          },
          "t_struct(OwnableStorage)13_storage": {
            "label": "struct OwnableUpgradeable.OwnableStorage",
            "members": [
              {
                "label": "_owner",
                "type": "t_address",
                "offset": 0,
                "slot": "0"
              }
            ],
            "numberOfBytes": "32"
          },
          "t_struct(ReentrancyGuardStorage)561_storage": {
            "label": "struct ReentrancyGuardUpgradeable.ReentrancyGuardStorage",
            "members": [
              {
                "label": "_status",
                "type": "t_uint256",
                "offset": 0,
                "slot": "0"
              }
            ],
            "numberOfBytes": "32"
          },
          "t_uint256": {
            "label": "uint256",
            "numberOfBytes": "32"
          },
          "t_uint64": {
            "label": "uint64",
            "numberOfBytes": "8"
          },
          "t_contract(IERC20)3152": {
            "label": "contract IERC20",
            "numberOfBytes": "20"
          },
          "t_mapping(t_uint256,t_string_storage)": {
            "label": "mapping(uint256 => string)",
            "numberOfBytes": "32"
          },
          "t_mapping(t_uint256,t_struct(Listing)8945_storage)": {
            "label": "mapping(uint256 => struct MarketplaceV1.Listing)",
            "numberOfBytes": "32"
          },
          "t_struct(Listing)8945_storage": {
            "label": "struct MarketplaceV1.Listing",
            "members": [
              {
                "label": "seller",
                "type": "t_address",
                "offset": 0,
                "slot": "0"
              },
              {
                "label": "price",
                "type": "t_uint256",
                "offset": 0,
                "slot": "1"
              },
              {
                "label": "active",
                "type": "t_bool",
                "offset": 0,
                "slot": "2"
              }
            ],
            "numberOfBytes": "96"
          }
        },
        "namespaces": {
          "erc7201:openzeppelin.storage.ReentrancyGuard": [
            {
              "contract": "ReentrancyGuardUpgradeable",
              "label": "_status",
              "type": "t_uint256",
              "src": "@openzeppelin\\contracts-upgradeable\\utils\\ReentrancyGuardUpgradeable.sol:43",
              "offset": 0,
              "slot": "0"
            }
          ],
          "erc7201:openzeppelin.storage.Ownable": [
            {
              "contract": "OwnableUpgradeable",
              "label": "_owner",
              "type": "t_address",
              "src": "@openzeppelin\\contracts-upgradeable\\access\\OwnableUpgradeable.sol:24",
              "offset": 0,
              "slot": "0"
            }
          ],
          "erc7201:openzeppelin.storage.ERC721": [
            {
              "contract": "ERC721Upgradeable",
              "label": "_name",
              "type": "t_string_storage",
              "src": "@openzeppelin\\contracts-upgradeable\\token\\ERC721\\ERC721Upgradeable.sol:27",
              "offset": 0,
              "slot": "0"
            },
            {
              "contract": "ERC721Upgradeable",
              "label": "_symbol",
              "type": "t_string_storage",
              "src": "@openzeppelin\\contracts-upgradeable\\token\\ERC721\\ERC721Upgradeable.sol:30",
              "offset": 0,
              "slot": "1"
            },
            {
              "contract": "ERC721Upgradeable",
              "label": "_owners",
              "type": "t_mapping(t_uint256,t_address)",
              "src": "@openzeppelin\\contracts-upgradeable\\token\\ERC721\\ERC721Upgradeable.sol:32",
              "offset": 0,
              "slot": "2"
            },
            {
              "contract": "ERC721Upgradeable",
              "label": "_balances",
              "type": "t_mapping(t_address,t_uint256)",
              "src": "@openzeppelin\\contracts-upgradeable\\token\\ERC721\\ERC721Upgradeable.sol:34",
              "offset": 0,
              "slot": "3"
            },
            {
              "contract": "ERC721Upgradeable",
              "label": "_tokenApprovals",
              "type": "t_mapping(t_uint256,t_address)",
              "src": "@openzeppelin\\contracts-upgradeable\\token\\ERC721\\ERC721Upgradeable.sol:36",
              "offset": 0,
              "slot": "4"
            },
            {
              "contract": "ERC721Upgradeable",
              "label": "_operatorApprovals",
              "type": "t_mapping(t_address,t_mapping(t_address,t_bool))",
              "src": "@openzeppelin\\contracts-upgradeable\\token\\ERC721\\ERC721Upgradeable.sol:38",
              "offset": 0,
              "slot": "5"
            }
          ],
          "erc7201:openzeppelin.storage.Initializable": [
            {
              "contract": "Initializable",
              "label": "_initialized",
              "type": "t_uint64",
              "src": "@openzeppelin\\contracts-upgradeable\\proxy\\utils\\Initializable.sol:69",
              "offset": 0,
              "slot": "0"
            },
            {
              "contract": "Initializable",
              "label": "_initializing",
              "type": "t_bool",
              "src": "@openzeppelin\\contracts-upgradeable\\proxy\\utils\\Initializable.sol:73",
              "offset": 8,
              "slot": "0"
            }
          ]
        }
      }
    },
    "d428c0c373ca128fe863c3390465ea1589533a70ed136c293d5a32baf3c23296": {
      "address": "0x35d1D572d28bD77b58f5C9F33381B108D6d7EE55",
      "txHash": "0x8bbdec665d83204c9969a9825add967d30a152ef0fe697e386c66779f8ba5274",
      "layout": {
        "solcVersion": "0.8.28",
        "storage": [
          {
            "label": "_tokenIdCounter",
            "offset": 0,
            "slot": "0",
            "type": "t_uint256",
            "contract": "MarketplaceV1_1",
            "src": "contracts\\MarketplaceV1_1.sol:13"
          },
          {
            "label": "paymentToken",
            "offset": 0,
            "slot": "1",
            "type": "t_contract(IERC20)3152",
            "contract": "MarketplaceV1_1",
            "src": "contracts\\MarketplaceV1_1.sol:14"
          },
          {
            "label": "_tokenURIs",
            "offset": 0,
            "slot": "2",
            "type": "t_mapping(t_uint256,t_string_storage)",
            "contract": "MarketplaceV1_1",
            "src": "contracts\\MarketplaceV1_1.sol:16"
          },
          {
            "label": "listings",
            "offset": 0,
            "slot": "3",
            "type": "t_mapping(t_uint256,t_struct(Listing)9352_storage)",
            "contract": "MarketplaceV1_1",
            "src": "contracts\\MarketplaceV1_1.sol:24"
          },
          {
            "label": "totalListings",
            "offset": 0,
            "slot": "4",
            "type": "t_uint256",
            "contract": "MarketplaceV1_1",
            "src": "contracts\\MarketplaceV1_1.sol:26"
          }
        ],
        "types": {
          "t_address": {
            "label": "address",
            "numberOfBytes": "20"
          },
          "t_bool": {
            "label": "bool",
            "numberOfBytes": "1"
          },
          "t_mapping(t_address,t_bool)": {
            "label": "mapping(address => bool)",
            "numberOfBytes": "32"
          },
          "t_mapping(t_address,t_mapping(t_address,t_bool))": {
            "label": "mapping(address => mapping(address => bool))",
            "numberOfBytes": "32"
          },
          "t_mapping(t_address,t_uint256)": {
            "label": "mapping(address => uint256)",
            "numberOfBytes": "32"
          },
          "t_mapping(t_uint256,t_address)": {
            "label": "mapping(uint256 => address)",
            "numberOfBytes": "32"
          },
          "t_string_storage": {
            "label": "string",
            "numberOfBytes": "32"
          },
          "t_struct(ERC721Storage)240_storage": {
            "label": "struct ERC721Upgradeable.ERC721Storage",
            "members": [
              {
                "label": "_name",
                "type": "t_string_storage",
                "offset": 0,
                "slot": "0"
              },
              {
                "label": "_symbol",
                "type": "t_string_storage",
                "offset": 0,
                "slot": "1"
              },
              {
                "label": "_owners",
                "type": "t_mapping(t_uint256,t_address)",
                "offset": 0,
                "slot": "2"
              },
              {
                "label": "_balances",
                "type": "t_mapping(t_address,t_uint256)",
                "offset": 0,
                "slot": "3"
              },
              {
                "label": "_tokenApprovals",
                "type": "t_mapping(t_uint256,t_address)",
                "offset": 0,
                "slot": "4"
              },
              {
                "label": "_operatorApprovals",
                "type": "t_mapping(t_address,t_mapping(t_address,t_bool))",
                "offset": 0,
                "slot": "5"
              }
            ],
            "numberOfBytes": "192"
          },
          "t_struct(InitializableStorage)73_storage": {
            "label": "struct Initializable.InitializableStorage",
            "members": [
              {
                "label": "_initialized",
                "type": "t_uint64",
                "offset": 0,
                "slot": "0"
              },
              {
                "label": "_initializing",
                "type": "t_bool",
                "offset": 8,
                "slot": "0"
              }
            ],
            "numberOfBytes": "32"
          },
          "t_struct(OwnableStorage)13_storage": {
            "label": "struct OwnableUpgradeable.OwnableStorage",
            "members": [
              {
                "label": "_owner",
                "type": "t_address",
                "offset": 0,
                "slot": "0"
              }
            ],
            "numberOfBytes": "32"
          },
          "t_struct(ReentrancyGuardStorage)561_storage": {
            "label": "struct ReentrancyGuardUpgradeable.ReentrancyGuardStorage",
            "members": [
              {
                "label": "_status",
                "type": "t_uint256",
                "offset": 0,
                "slot": "0"
              }
            ],
            "numberOfBytes": "32"
          },
          "t_uint256": {
            "label": "uint256",
            "numberOfBytes": "32"
          },
          "t_uint64": {
            "label": "uint64",
            "numberOfBytes": "8"
          },
          "t_contract(IERC20)3152": {
            "label": "contract IERC20",
            "numberOfBytes": "20"
          },
          "t_mapping(t_uint256,t_string_storage)": {
            "label": "mapping(uint256 => string)",
            "numberOfBytes": "32"
          },
          "t_mapping(t_uint256,t_struct(Listing)9352_storage)": {
            "label": "mapping(uint256 => struct MarketplaceV1_1.Listing)",
            "numberOfBytes": "32"
          },
          "t_struct(Listing)9352_storage": {
            "label": "struct MarketplaceV1_1.Listing",
            "members": [
              {
                "label": "seller",
                "type": "t_address",
                "offset": 0,
                "slot": "0"
              },
              {
                "label": "price",
                "type": "t_uint256",
                "offset": 0,
                "slot": "1"
              },
              {
                "label": "active",
                "type": "t_bool",
                "offset": 0,
                "slot": "2"
              }
            ],
            "numberOfBytes": "96"
          }
        },
        "namespaces": {
          "erc7201:openzeppelin.storage.ReentrancyGuard": [
            {
              "contract": "ReentrancyGuardUpgradeable",
              "label": "_status",
              "type": "t_uint256",
              "src": "@openzeppelin\\contracts-upgradeable\\utils\\ReentrancyGuardUpgradeable.sol:43",
              "offset": 0,
              "slot": "0"
            }
          ],
          "erc7201:openzeppelin.storage.Ownable": [
            {
              "contract": "OwnableUpgradeable",
              "label": "_owner",
              "type": "t_address",
              "src": "@openzeppelin\\contracts-upgradeable\\access\\OwnableUpgradeable.sol:24",
              "offset": 0,
              "slot": "0"
            }
          ],
          "erc7201:openzeppelin.storage.ERC721": [
            {
              "contract": "ERC721Upgradeable",
              "label": "_name",
              "type": "t_string_storage",
              "src": "@openzeppelin\\contracts-upgradeable\\token\\ERC721\\ERC721Upgradeable.sol:27",
              "offset": 0,
              "slot": "0"
            },
            {
              "contract": "ERC721Upgradeable",
              "label": "_symbol",
              "type": "t_string_storage",
              "src": "@openzeppelin\\contracts-upgradeable\\token\\ERC721\\ERC721Upgradeable.sol:30",
              "offset": 0,
              "slot": "1"
            },
            {
              "contract": "ERC721Upgradeable",
              "label": "_owners",
              "type": "t_mapping(t_uint256,t_address)",
              "src": "@openzeppelin\\contracts-upgradeable\\token\\ERC721\\ERC721Upgradeable.sol:32",
              "offset": 0,
              "slot": "2"
            },
            {
              "contract": "ERC721Upgradeable",
              "label": "_balances",
              "type": "t_mapping(t_address,t_uint256)",
              "src": "@openzeppelin\\contracts-upgradeable\\token\\ERC721\\ERC721Upgradeable.sol:34",
              "offset": 0,
              "slot": "3"
            },
            {
              "contract": "ERC721Upgradeable",
              "label": "_tokenApprovals",
              "type": "t_mapping(t_uint256,t_address)",
              "src": "@openzeppelin\\contracts-upgradeable\\token\\ERC721\\ERC721Upgradeable.sol:36",
              "offset": 0,
              "slot": "4"
            },
            {
              "contract": "ERC721Upgradeable",
              "label": "_operatorApprovals",
              "type": "t_mapping(t_address,t_mapping(t_address,t_bool))",
              "src": "@openzeppelin\\contracts-upgradeable\\token\\ERC721\\ERC721Upgradeable.sol:38",
              "offset": 0,
              "slot": "5"
            }
          ],
          "erc7201:openzeppelin.storage.Initializable": [
            {
              "contract": "Initializable",
              "label": "_initialized",
              "type": "t_uint64",
              "src": "@openzeppelin\\contracts-upgradeable\\proxy\\utils\\Initializable.sol:69",
              "offset": 0,
              "slot": "0"
            },
            {
              "contract": "Initializable",
              "label": "_initializing",
              "type": "t_bool",
              "src": "@openzeppelin\\contracts-upgradeable\\proxy\\utils\\Initializable.sol:73",
              "offset": 8,
              "slot": "0"
            }
          ]
        }
      }
    },
    "0fddfe711d145e555f21aaa7180dcf7dbbb5aa9ff5728a9c4e0a6438384ffb62": {
      "address": "0x7A513f5Da94B1e8bCaB3B6BFA7df2103BE568308",
      "txHash": "0x45c9eaf9de0aa49604cf601812c7b0656784683153634c03e5b15a1807c29c9b",
      "layout": {
        "solcVersion": "0.8.28",
        "storage": [
          {
            "label": "_tokenIdCounter",
            "offset": 0,
            "slot": "0",
            "type": "t_uint256",
            "contract": "MarketplaceV1_1",
            "src": "contracts\\MarketplaceV1_1.sol:13"
          },
          {
            "label": "paymentToken",
            "offset": 0,
            "slot": "1",
            "type": "t_contract(IERC20)3152",
            "contract": "MarketplaceV1_1",
            "src": "contracts\\MarketplaceV1_1.sol:14"
          },
          {
            "label": "_tokenURIs",
            "offset": 0,
            "slot": "2",
            "type": "t_mapping(t_uint256,t_string_storage)",
            "contract": "MarketplaceV1_1",
            "src": "contracts\\MarketplaceV1_1.sol:16"
          },
          {
            "label": "listings",
            "offset": 0,
            "slot": "3",
            "type": "t_mapping(t_uint256,t_struct(Listing)9352_storage)",
            "contract": "MarketplaceV1_1",
            "src": "contracts\\MarketplaceV1_1.sol:24"
          },
          {
            "label": "totalListings",
            "offset": 0,
            "slot": "4",
            "type": "t_uint256",
            "contract": "MarketplaceV1_1",
            "src": "contracts\\MarketplaceV1_1.sol:26"
          },
          {
            "label": "commissionBps",
            "offset": 0,
            "slot": "5",
            "type": "t_uint16",
            "contract": "MarketplaceV1_1",
            "src": "contracts\\MarketplaceV1_1.sol:30"
          },
          {
            "label": "commissionRecipient",
            "offset": 2,
            "slot": "5",
            "type": "t_address",
            "contract": "MarketplaceV1_1",
            "src": "contracts\\MarketplaceV1_1.sol:31"
          }
        ],
        "types": {
          "t_address": {
            "label": "address",
            "numberOfBytes": "20"
          },
          "t_bool": {
            "label": "bool",
            "numberOfBytes": "1"
          },
          "t_mapping(t_address,t_bool)": {
            "label": "mapping(address => bool)",
            "numberOfBytes": "32"
          },
          "t_mapping(t_address,t_mapping(t_address,t_bool))": {
            "label": "mapping(address => mapping(address => bool))",
            "numberOfBytes": "32"
          },
          "t_mapping(t_address,t_uint256)": {
            "label": "mapping(address => uint256)",
            "numberOfBytes": "32"
          },
          "t_mapping(t_uint256,t_address)": {
            "label": "mapping(uint256 => address)",
            "numberOfBytes": "32"
          },
          "t_string_storage": {
            "label": "string",
            "numberOfBytes": "32"
          },
          "t_struct(ERC721Storage)240_storage": {
            "label": "struct ERC721Upgradeable.ERC721Storage",
            "members": [
              {
                "label": "_name",
                "type": "t_string_storage",
                "offset": 0,
                "slot": "0"
              },
              {
                "label": "_symbol",
                "type": "t_string_storage",
                "offset": 0,
                "slot": "1"
              },
              {
                "label": "_owners",
                "type": "t_mapping(t_uint256,t_address)",
                "offset": 0,
                "slot": "2"
              },
              {
                "label": "_balances",
                "type": "t_mapping(t_address,t_uint256)",
                "offset": 0,
                "slot": "3"
              },
              {
                "label": "_tokenApprovals",
                "type": "t_mapping(t_uint256,t_address)",
                "offset": 0,
                "slot": "4"
              },
              {
                "label": "_operatorApprovals",
                "type": "t_mapping(t_address,t_mapping(t_address,t_bool))",
                "offset": 0,
                "slot": "5"
              }
            ],
            "numberOfBytes": "192"
          },
          "t_struct(InitializableStorage)73_storage": {
            "label": "struct Initializable.InitializableStorage",
            "members": [
              {
                "label": "_initialized",
                "type": "t_uint64",
                "offset": 0,
                "slot": "0"
              },
              {
                "label": "_initializing",
                "type": "t_bool",
                "offset": 8,
                "slot": "0"
              }
            ],
            "numberOfBytes": "32"
          },
          "t_struct(OwnableStorage)13_storage": {
            "label": "struct OwnableUpgradeable.OwnableStorage",
            "members": [
              {
                "label": "_owner",
                "type": "t_address",
                "offset": 0,
                "slot": "0"
              }
            ],
            "numberOfBytes": "32"
          },
          "t_struct(ReentrancyGuardStorage)561_storage": {
            "label": "struct ReentrancyGuardUpgradeable.ReentrancyGuardStorage",
            "members": [
              {
                "label": "_status",
                "type": "t_uint256",
                "offset": 0,
                "slot": "0"
              }
            ],
            "numberOfBytes": "32"
          },
          "t_uint256": {
            "label": "uint256",
            "numberOfBytes": "32"
          },
          "t_uint64": {
            "label": "uint64",
            "numberOfBytes": "8"
          },
          "t_contract(IERC20)3152": {
            "label": "contract IERC20",
            "numberOfBytes": "20"
          },
          "t_mapping(t_uint256,t_string_storage)": {
            "label": "mapping(uint256 => string)",
            "numberOfBytes": "32"
          },
          "t_mapping(t_uint256,t_struct(Listing)9352_storage)": {
            "label": "mapping(uint256 => struct MarketplaceV1_1.Listing)",
            "numberOfBytes": "32"
          },
          "t_struct(Listing)9352_storage": {
            "label": "struct MarketplaceV1_1.Listing",
            "members": [
              {
                "label": "seller",
                "type": "t_address",
                "offset": 0,
                "slot": "0"
              },
              {
                "label": "price",
                "type": "t_uint256",
                "offset": 0,
                "slot": "1"
              },
              {
                "label": "active",
                "type": "t_bool",
                "offset": 0,
                "slot": "2"
              }
            ],
            "numberOfBytes": "96"
          },
          "t_uint16": {
            "label": "uint16",
            "numberOfBytes": "2"
          }
        },
        "namespaces": {
          "erc7201:openzeppelin.storage.ReentrancyGuard": [
            {
              "contract": "ReentrancyGuardUpgradeable",
              "label": "_status",
              "type": "t_uint256",
              "src": "@openzeppelin\\contracts-upgradeable\\utils\\ReentrancyGuardUpgradeable.sol:43",
              "offset": 0,
              "slot": "0"
            }
          ],
          "erc7201:openzeppelin.storage.Ownable": [
            {
              "contract": "OwnableUpgradeable",
              "label": "_owner",
              "type": "t_address",
              "src": "@openzeppelin\\contracts-upgradeable\\access\\OwnableUpgradeable.sol:24",
              "offset": 0,
              "slot": "0"
            }
          ],
          "erc7201:openzeppelin.storage.ERC721": [
            {
              "contract": "ERC721Upgradeable",
              "label": "_name",
              "type": "t_string_storage",
              "src": "@openzeppelin\\contracts-upgradeable\\token\\ERC721\\ERC721Upgradeable.sol:27",
              "offset": 0,
              "slot": "0"
            },
            {
              "contract": "ERC721Upgradeable",
              "label": "_symbol",
              "type": "t_string_storage",
              "src": "@openzeppelin\\contracts-upgradeable\\token\\ERC721\\ERC721Upgradeable.sol:30",
              "offset": 0,
              "slot": "1"
            },
            {
              "contract": "ERC721Upgradeable",
              "label": "_owners",
              "type": "t_mapping(t_uint256,t_address)",
              "src": "@openzeppelin\\contracts-upgradeable\\token\\ERC721\\ERC721Upgradeable.sol:32",
              "offset": 0,
              "slot": "2"
            },
            {
              "contract": "ERC721Upgradeable",
              "label": "_balances",
              "type": "t_mapping(t_address,t_uint256)",
              "src": "@openzeppelin\\contracts-upgradeable\\token\\ERC721\\ERC721Upgradeable.sol:34",
              "offset": 0,
              "slot": "3"
            },
            {
              "contract": "ERC721Upgradeable",
              "label": "_tokenApprovals",
              "type": "t_mapping(t_uint256,t_address)",
              "src": "@openzeppelin\\contracts-upgradeable\\token\\ERC721\\ERC721Upgradeable.sol:36",
              "offset": 0,
              "slot": "4"
            },
            {
              "contract": "ERC721Upgradeable",
              "label": "_operatorApprovals",
              "type": "t_mapping(t_address,t_mapping(t_address,t_bool))",
              "src": "@openzeppelin\\contracts-upgradeable\\token\\ERC721\\ERC721Upgradeable.sol:38",
              "offset": 0,
              "slot": "5"
            }
          ],
          "erc7201:openzeppelin.storage.Initializable": [
            {
              "contract": "Initializable",
              "label": "_initialized",
              "type": "t_uint64",
              "src": "@openzeppelin\\contracts-upgradeable\\proxy\\utils\\Initializable.sol:69",
              "offset": 0,
              "slot": "0"
            },
            {
              "contract": "Initializable",
              "label": "_initializing",
              "type": "t_bool",
              "src": "@openzeppelin\\contracts-upgradeable\\proxy\\utils\\Initializable.sol:73",
              "offset": 8,
              "slot": "0"
            }
          ]
        }
      }
    },
    "52ce308bad3ef930a2577516e0057820a9a821dd131d19a1fa59fcdffb1fa6a5": {
      "address": "0x9dcB91cD7d665D140C84E7c3020D0bEBc6C02C97",
      "txHash": "0xaced070d8023395383d6b0a5fb66e937d29eacc45a65a078a3fc7287a94918d7",
      "layout": {
        "solcVersion": "0.8.28",
        "storage": [
          {
            "label": "_tokenIdCounter",
            "offset": 0,
            "slot": "0",
            "type": "t_uint256",
            "contract": "MarketplaceV1_1",
            "src": "contracts\\MarketplaceV1_1.sol:20"
          },
          {
            "label": "paymentToken",
            "offset": 0,
            "slot": "1",
            "type": "t_contract(IERC20)3508",
            "contract": "MarketplaceV1_1",
            "src": "contracts\\MarketplaceV1_1.sol:21"
          },
          {
            "label": "_tokenURIs",
            "offset": 0,
            "slot": "2",
            "type": "t_mapping(t_uint256,t_string_storage)",
            "contract": "MarketplaceV1_1",
            "src": "contracts\\MarketplaceV1_1.sol:23"
          },
          {
            "label": "listings",
            "offset": 0,
            "slot": "3",
            "type": "t_mapping(t_uint256,t_struct(Listing)9711_storage)",
            "contract": "MarketplaceV1_1",
            "src": "contracts\\MarketplaceV1_1.sol:31"
          },
          {
            "label": "totalListings",
            "offset": 0,
            "slot": "4",
            "type": "t_uint256",
            "contract": "MarketplaceV1_1",
            "src": "contracts\\MarketplaceV1_1.sol:32"
          },
          {
            "label": "commissionBps",
            "offset": 0,
            "slot": "5",
            "type": "t_uint16",
            "contract": "MarketplaceV1_1",
            "src": "contracts\\MarketplaceV1_1.sol:35"
          },
          {
            "label": "commissionRecipient",
            "offset": 2,
            "slot": "5",
            "type": "t_address",
            "contract": "MarketplaceV1_1",
            "src": "contracts\\MarketplaceV1_1.sol:36"
          }
        ],
        "types": {
          "t_address": {
            "label": "address",
            "numberOfBytes": "20"
          },
          "t_bool": {
            "label": "bool",
            "numberOfBytes": "1"
          },
          "t_mapping(t_address,t_bool)": {
            "label": "mapping(address => bool)",
            "numberOfBytes": "32"
          },
          "t_mapping(t_address,t_mapping(t_address,t_bool))": {
            "label": "mapping(address => mapping(address => bool))",
            "numberOfBytes": "32"
          },
          "t_mapping(t_address,t_uint256)": {
            "label": "mapping(address => uint256)",
            "numberOfBytes": "32"
          },
          "t_mapping(t_uint256,t_address)": {
            "label": "mapping(uint256 => address)",
            "numberOfBytes": "32"
          },
          "t_mapping(t_uint256,t_struct(RoyaltyInfo)538_storage)": {
            "label": "mapping(uint256 => struct ERC2981Upgradeable.RoyaltyInfo)",
            "numberOfBytes": "32"
          },
          "t_string_storage": {
            "label": "string",
            "numberOfBytes": "32"
          },
          "t_struct(ERC2981Storage)548_storage": {
            "label": "struct ERC2981Upgradeable.ERC2981Storage",
            "members": [
              {
                "label": "_defaultRoyaltyInfo",
                "type": "t_struct(RoyaltyInfo)538_storage",
                "offset": 0,
                "slot": "0"
              },
              {
                "label": "_tokenRoyaltyInfo",
                "type": "t_mapping(t_uint256,t_struct(RoyaltyInfo)538_storage)",
                "offset": 0,
                "slot": "1"
              }
            ],
            "numberOfBytes": "64"
          },
          "t_struct(ERC721Storage)240_storage": {
            "label": "struct ERC721Upgradeable.ERC721Storage",
            "members": [
              {
                "label": "_name",
                "type": "t_string_storage",
                "offset": 0,
                "slot": "0"
              },
              {
                "label": "_symbol",
                "type": "t_string_storage",
                "offset": 0,
                "slot": "1"
              },
              {
                "label": "_owners",
                "type": "t_mapping(t_uint256,t_address)",
                "offset": 0,
                "slot": "2"
              },
              {
                "label": "_balances",
                "type": "t_mapping(t_address,t_uint256)",
                "offset": 0,
                "slot": "3"
              },
              {
                "label": "_tokenApprovals",
                "type": "t_mapping(t_uint256,t_address)",
                "offset": 0,
                "slot": "4"
              },
              {
                "label": "_operatorApprovals",
                "type": "t_mapping(t_address,t_mapping(t_address,t_bool))",
                "offset": 0,
                "slot": "5"
              }
            ],
            "numberOfBytes": "192"
          },
          "t_struct(InitializableStorage)73_storage": {
            "label": "struct Initializable.InitializableStorage",
            "members": [
              {
                "label": "_initialized",
                "type": "t_uint64",
                "offset": 0,
                "slot": "0"
              },
              {
                "label": "_initializing",
                "type": "t_bool",
                "offset": 8,
                "slot": "0"
              }
            ],
            "numberOfBytes": "32"
          },
          "t_struct(OwnableStorage)13_storage": {
            "label": "struct OwnableUpgradeable.OwnableStorage",
            "members": [
              {
                "label": "_owner",
                "type": "t_address",
                "offset": 0,
                "slot": "0"
              }
            ],
            "numberOfBytes": "32"
          },
          "t_struct(ReentrancyGuardStorage)669_storage": {
            "label": "struct ReentrancyGuardUpgradeable.ReentrancyGuardStorage",
            "members": [
              {
                "label": "_status",
                "type": "t_uint256",
                "offset": 0,
                "slot": "0"
              }
            ],
            "numberOfBytes": "32"
          },
          "t_struct(RoyaltyInfo)538_storage": {
            "label": "struct ERC2981Upgradeable.RoyaltyInfo",
            "members": [
              {
                "label": "receiver",
                "type": "t_address",
                "offset": 0,
                "slot": "0"
              },
              {
                "label": "royaltyFraction",
                "type": "t_uint96",
                "offset": 20,
                "slot": "0"
              }
            ],
            "numberOfBytes": "32"
          },
          "t_uint256": {
            "label": "uint256",
            "numberOfBytes": "32"
          },
          "t_uint64": {
            "label": "uint64",
            "numberOfBytes": "8"
          },
          "t_uint96": {
            "label": "uint96",
            "numberOfBytes": "12"
          },
          "t_contract(IERC20)3508": {
            "label": "contract IERC20",
            "numberOfBytes": "20"
          },
          "t_mapping(t_uint256,t_string_storage)": {
            "label": "mapping(uint256 => string)",
            "numberOfBytes": "32"
          },
          "t_mapping(t_uint256,t_struct(Listing)9711_storage)": {
            "label": "mapping(uint256 => struct MarketplaceV1_1.Listing)",
            "numberOfBytes": "32"
          },
          "t_struct(Listing)9711_storage": {
            "label": "struct MarketplaceV1_1.Listing",
            "members": [
              {
                "label": "seller",
                "type": "t_address",
                "offset": 0,
                "slot": "0"
              },
              {
                "label": "price",
                "type": "t_uint256",
                "offset": 0,
                "slot": "1"
              },
              {
                "label": "active",
                "type": "t_bool",
                "offset": 0,
                "slot": "2"
              }
            ],
            "numberOfBytes": "96"
          },
          "t_uint16": {
            "label": "uint16",
            "numberOfBytes": "2"
          }
        },
        "namespaces": {
          "erc7201:openzeppelin.storage.ReentrancyGuard": [
            {
              "contract": "ReentrancyGuardUpgradeable",
              "label": "_status",
              "type": "t_uint256",
              "src": "@openzeppelin\\contracts-upgradeable\\utils\\ReentrancyGuardUpgradeable.sol:43",
              "offset": 0,
              "slot": "0"
            }
          ],
          "erc7201:openzeppelin.storage.Ownable": [
            {
              "contract": "OwnableUpgradeable",
              "label": "_owner",
              "type": "t_address",
              "src": "@openzeppelin\\contracts-upgradeable\\access\\OwnableUpgradeable.sol:24",
              "offset": 0,
              "slot": "0"
            }
          ],
          "erc7201:openzeppelin.storage.ERC2981": [
            {
              "contract": "ERC2981Upgradeable",
              "label": "_defaultRoyaltyInfo",
              "type": "t_struct(RoyaltyInfo)538_storage",
              "src": "@openzeppelin\\contracts-upgradeable\\token\\common\\ERC2981Upgradeable.sol:32",
              "offset": 0,
              "slot": "0"
            },
            {
              "contract": "ERC2981Upgradeable",
              "label": "_tokenRoyaltyInfo",
              "type": "t_mapping(t_uint256,t_struct(RoyaltyInfo)538_storage)",
              "src": "@openzeppelin\\contracts-upgradeable\\token\\common\\ERC2981Upgradeable.sol:33",
              "offset": 0,
              "slot": "1"
            }
          ],
          "erc7201:openzeppelin.storage.ERC721": [
            {
              "contract": "ERC721Upgradeable",
              "label": "_name",
              "type": "t_string_storage",
              "src": "@openzeppelin\\contracts-upgradeable\\token\\ERC721\\ERC721Upgradeable.sol:27",
              "offset": 0,
              "slot": "0"
            },
            {
              "contract": "ERC721Upgradeable",
              "label": "_symbol",
              "type": "t_string_storage",
              "src": "@openzeppelin\\contracts-upgradeable\\token\\ERC721\\ERC721Upgradeable.sol:30",
              "offset": 0,
              "slot": "1"
            },
            {
              "contract": "ERC721Upgradeable",
              "label": "_owners",
              "type": "t_mapping(t_uint256,t_address)",
              "src": "@openzeppelin\\contracts-upgradeable\\token\\ERC721\\ERC721Upgradeable.sol:32",
              "offset": 0,
              "slot": "2"
            },
            {
              "contract": "ERC721Upgradeable",
              "label": "_balances",
              "type": "t_mapping(t_address,t_uint256)",
              "src": "@openzeppelin\\contracts-upgradeable\\token\\ERC721\\ERC721Upgradeable.sol:34",
              "offset": 0,
              "slot": "3"
            },
            {
              "contract": "ERC721Upgradeable",
              "label": "_tokenApprovals",
              "type": "t_mapping(t_uint256,t_address)",
              "src": "@openzeppelin\\contracts-upgradeable\\token\\ERC721\\ERC721Upgradeable.sol:36",
              "offset": 0,
              "slot": "4"
            },
            {
              "contract": "ERC721Upgradeable",
              "label": "_operatorApprovals",
              "type": "t_mapping(t_address,t_mapping(t_address,t_bool))",
              "src": "@openzeppelin\\contracts-upgradeable\\token\\ERC721\\ERC721Upgradeable.sol:38",
              "offset": 0,
              "slot": "5"
            }
          ],
          "erc7201:openzeppelin.storage.Initializable": [
            {
              "contract": "Initializable",
              "label": "_initialized",
              "type": "t_uint64",
              "src": "@openzeppelin\\contracts-upgradeable\\proxy\\utils\\Initializable.sol:69",
              "offset": 0,
              "slot": "0"
            },
            {
              "contract": "Initializable",
              "label": "_initializing",
              "type": "t_bool",
              "src": "@openzeppelin\\contracts-upgradeable\\proxy\\utils\\Initializable.sol:73",
              "offset": 8,
              "slot": "0"
            }
          ]
        }
      }
    }
  }
}
